{"nodes": [{"id": "workflows_ci_main", "label": "GitHub Workflow - CI Main/Release", "file_type": "document", "source_file": ".github/workflows/ci-main.yaml", "source_location": null, "source_url": null, "captured_at": null, "author": "Google LLC", "contributor": null}], "edges": [{"source": "workflows_ci_main", "target": "concept_skaffold", "relation": "uses", "confidence": "EXTRACTED", "confidence_score": 1.0, "source_file": ".github/workflows/ci-main.yaml", "source_location": "line 83", "weight": 1.0}, {"source": "workflows_ci_main", "target": "concept_gke", "relation": "uses", "confidence": "EXTRACTED", "confidence_score": 1.0, "source_file": ".github/workflows/ci-main.yaml", "source_location": "line 74", "weight": 1.0}], "hyperedges": []}